README.txt
setup.py
archetypes/__init__.py
archetypes.recurringdate.egg-info/PKG-INFO
archetypes.recurringdate.egg-info/SOURCES.txt
archetypes.recurringdate.egg-info/dependency_links.txt
archetypes.recurringdate.egg-info/entry_points.txt
archetypes.recurringdate.egg-info/namespace_packages.txt
archetypes.recurringdate.egg-info/not-zip-safe
archetypes.recurringdate.egg-info/requires.txt
archetypes.recurringdate.egg-info/top_level.txt
archetypes/recurringdate/__init__.py
archetypes/recurringdate/configure.zcml
archetypes/recurringdate/field.py
archetypes/recurringdate/recurrence.py
archetypes/recurringdate/version.txt
archetypes/recurringdate/widget.py
archetypes/recurringdate/profiles/default/metadata.xml
archetypes/recurringdate/profiles/default/skins.xml
archetypes/recurringdate/skins/recurringdate/datejs.js
archetypes/recurringdate/skins/recurringdate/datepicker.css
archetypes/recurringdate/skins/recurringdate/recurring_date.css.dtml
archetypes/recurringdate/skins/recurringdate/recurring_date.js
archetypes/recurringdate/skins/recurringdate/recurring_date.pt
archetypes/recurringdate/skins/recurringdate/ui.datepicker.js
archetypes/recurringdate/skins/recurringdate/ui.timepicker.js
archetypes/recurringdate/skins/recurringdate/ui_images/custom_b.png
archetypes/recurringdate/skins/recurringdate/ui_images/custom_bl.png
archetypes/recurringdate/skins/recurringdate/ui_images/custom_br.png
archetypes/recurringdate/skins/recurringdate/ui_images/custom_l.png
archetypes/recurringdate/skins/recurringdate/ui_images/custom_r.png
archetypes/recurringdate/skins/recurringdate/ui_images/custom_t.png
archetypes/recurringdate/skins/recurringdate/ui_images/custom_tl.png
archetypes/recurringdate/skins/recurringdate/ui_images/custom_tr.png
archetypes/recurringdate/skins/recurringdate/ui_images/datepicker_b.png
archetypes/recurringdate/skins/recurringdate/ui_images/datepicker_bl.png
archetypes/recurringdate/skins/recurringdate/ui_images/datepicker_br.png
archetypes/recurringdate/skins/recurringdate/ui_images/datepicker_l.png
archetypes/recurringdate/skins/recurringdate/ui_images/datepicker_r.png
archetypes/recurringdate/skins/recurringdate/ui_images/datepicker_t.png
archetypes/recurringdate/skins/recurringdate/ui_images/datepicker_tl.png
archetypes/recurringdate/skins/recurringdate/ui_images/datepicker_tr.png
archetypes/recurringdate/skins/recurringdate/ui_images/field.png
