Metadata-Version: 1.0
Name: archetypes.recurringdate
Version: 0.2
Summary: Field/Widget to support recurring dates.
Home-page: http://dev.plone.org/archetypes/log/MoreFieldsAndWidgets/archetypes.recurringdate
Author: Dorneles Tremea
Author-email: dorneles@tremea.com
License: GPL
Keywords: date recurring archetypes field widget
Platform: UNKNOWN
Classifier: Environment :: Web Environment
Classifier: Framework :: Plone
Classifier: Framework :: Zope2
Classifier: Programming Language :: Python
Classifier: License :: OSI Approved :: GNU General Public License (GPL)
Classifier: Operating System :: OS Independent
Classifier: Topic :: Internet :: WWW/HTTP :: Dynamic Content
